{"ID":6695,"Author":{"Name":"rcmdnk","ID":0,"FullName":"","Gravatar":"11242b5070dab7cfdf020119391bf606"},"Title":"Selection window demo of multi_clipboard","Description":"\u003cdiv class=\"content\"\u003e\u003cp\u003eRef:\u003c/p\u003e\n\n\u003cul\u003e\n\u003cli\u003e\u003ca href=\"https://github.com/rcmdnk/multi_clipboard/\"\u003emulti_clipbaord\u003c/a\u003e\u003c/li\u003e\n\u003cli\u003e\u003ca href=\"http://rcmdnk.github.io/blog/2013/12/04/computer-screen/\"\u003eBlog\u003c/a\u003e\u003c/li\u003e\n\u003c/ul\u003e\n\u003c/div\u003e","Time":"2013-12-09T23:33:24Z","Tags":["OS X","bash","xterm-256color"]}